drtvam/__init__.py
drtvam/film.py
drtvam/geometry.py
drtvam/lbfgs.py
drtvam/loss.py
drtvam/motion.py
drtvam/optimize.py
drtvam/projector.py
drtvam/sensor.py
drtvam/utils.py
drtvam/integrators/__init__.py
drtvam/integrators/common.py
drtvam/integrators/filter_corner.py
drtvam/integrators/radon.py
drtvam/integrators/volume.py
drtvam-0.7.0.dist-info/licenses/LICENSE
drtvam-0.7.0.dist-info/METADATA
drtvam-0.7.0.dist-info/WHEEL
drtvam-0.7.0.dist-info/entry_points.txt
drtvam-0.7.0.dist-info/top_level.txt
drtvam-0.7.0.dist-info/RECORD
