Metadata-Version: 2.4
Name: drtvam
Version: 0.7.0
Summary: An inverse rendering framework for tomographic volumetric additive manufacturing
Author-email: Baptiste Nicolet <baptiste.nicolet@epfl.ch>, Felix Wechsler <fxw+git@mailbox.org>
Project-URL: Homepage, https://github.com/rgl-epfl/drtvam
Project-URL: Issues, https://github.com/rgl-epfl/drtvam/issues
Classifier: Programming Language :: Python :: 3
Classifier: Operating System :: OS Independent
Requires-Python: >=3.9
License-File: LICENSE
Requires-Dist: mitsuba==3.7.0
Requires-Dist: numpy
Requires-Dist: tqdm
Requires-Dist: matplotlib
Requires-Dist: scipy
Dynamic: license-file
